mai_dx/__init__.py
mai_dx/main.py
mai_dx-0.0.1.dist-info/LICENSE
mai_dx-0.0.1.dist-info/METADATA
mai_dx-0.0.1.dist-info/WHEEL
mai_dx-0.0.1.dist-info/RECORD
